hello.py
smtpkg777/__init__.py
smtpkg777/__main__.py
smtpkg777/camera/__init__.py
smtpkg777/camera/camera.py
smtpkg777/phone/__init__.py
smtpkg777/phone/phone.py
smtpkg3437-1.0.0.dist-info/METADATA
smtpkg3437-1.0.0.dist-info/WHEEL
smtpkg3437-1.0.0.dist-info/top_level.txt
smtpkg3437-1.0.0.dist-info/RECORD
