Metadata-Version: 2.1
Name: smtpkg3437
Version: 1.0.0
Summary: about smartphone
Home-page: https://pypi.org/p/twine/
Author: gop
Author-email: UNKNOWN
License: UNKNOWN
Platform: UNKNOWN
